dxrsubscriber/__init__.py
dxrsubscriber/subscriber.py
dxrsubscriber-0.0.0.dist-info/METADATA
dxrsubscriber-0.0.0.dist-info/WHEEL
dxrsubscriber-0.0.0.dist-info/top_level.txt
dxrsubscriber-0.0.0.dist-info/RECORD
