Metadata-Version: 2.1
Name: dxrsubscriber
Version: 0.0.0
Summary: A ZMQ subscriber for receiving and decoding video streams.
Home-page: https://github.com/yourusername/zmq_subscriber
Author: Your Name
Author-email: your.email@example.com
Classifier: Programming Language :: Python :: 3
Classifier: License :: OSI Approved :: MIT License
Classifier: Operating System :: OS Independent
Requires-Python: >=3.6
Requires-Dist: pyzmq
Requires-Dist: av
Requires-Dist: opencv-python (==4.5.1.48)
